sharepointer/__init__.py
sharepointer/sharepoint.py
sharepointer-0.1.2.dist-info/METADATA
sharepointer-0.1.2.dist-info/WHEEL
sharepointer-0.1.2.dist-info/RECORD
