Metadata-Version: 2.4
Name: sharepointer
Version: 0.1.2
Summary: A tool to manage SharePoint files and folders.
Project-URL: Homepage, https://github.com/woutervriel/sharepointmanager
Project-URL: Repository, https://github.com/woutervriel/sharepointmanager.git
Project-URL: Bug Tracker, https://github.com/woutervriel/sharepointmanager/issues
Author-email: Wouter van Riel <wouter.van.riel@infralytics.org>
License: MIT
Keywords: automation,file-management,office365,python,sharepoint
Classifier: Development Status :: 3 - Alpha
Classifier: Intended Audience :: Developers
Classifier: License :: OSI Approved :: MIT License
Classifier: Operating System :: OS Independent
Classifier: Programming Language :: Python :: 3
Classifier: Programming Language :: Python :: 3.13
Classifier: Topic :: Office/Business
Requires-Python: >=3.13
Requires-Dist: msal>=1.33.0
Requires-Dist: office365-rest-python-client>=2.6.2
Requires-Dist: python-dotenv>=1.2.1
Provides-Extra: dev
Requires-Dist: coverage>=7.11.0; extra == 'dev'
Requires-Dist: pytest-cov>=7.0.0; extra == 'dev'
Requires-Dist: pytest>=8.4.2; extra == 'dev'
